README.rst
cmdstats.py
setup.py
cmdstats.egg-info/PKG-INFO
cmdstats.egg-info/SOURCES.txt
cmdstats.egg-info/dependency_links.txt
cmdstats.egg-info/entry_points.txt
cmdstats.egg-info/not-zip-safe
cmdstats.egg-info/pbr.json
cmdstats.egg-info/requires.txt
cmdstats.egg-info/top_level.txt