Metadata-Version: 1.1
Name: cmdstats
Version: 0.3
Summary: 
Author: JackeyGao
